focus_response/__init__.py
focus_response/batch.py
focus_response/filters.py
focus_response/focus_response.py
focus_response/kde.py
focus_response/visualization.py
focus_response-0.1.5.dist-info/LICENSE
focus_response-0.1.5.dist-info/METADATA
focus_response-0.1.5.dist-info/WHEEL
focus_response-0.1.5.dist-info/top_level.txt
focus_response-0.1.5.dist-info/RECORD
